maxmcp/__init__.py
maxmcp/client.py
maxmcp/exchange.py
maxmcp/py.typed
maxmcp/server.py
maxmcp/types/__init__.py
maxmcp/types/account.py
maxmcp/types/currency.py
maxmcp/types/market.py
maxmcp/types/order.py
maxmcp/types/ticker.py
maxmcp-0.1.0.dist-info/METADATA
maxmcp-0.1.0.dist-info/WHEEL
maxmcp-0.1.0.dist-info/entry_points.txt
maxmcp-0.1.0.dist-info/licenses/LICENSE
maxmcp-0.1.0.dist-info/RECORD
